{
  "gitSyncId": "649135437cb8515629f9868a_649135487cb8515629f98781",
  "id": "SnowflakeDB_Page_Query1",
  "pluginId": "mysql-plugin",
  "pluginType": "DB",
  "unpublishedAction": {
    "actionConfiguration": {
      "body": "SELECT * FROM users where role = 'Admin' ORDER BY id LIMIT 10\n",
      "encodeParamsToggle": true,
      "paginationType": "NONE",
      "pluginSpecifiedTemplates": [
        {
          "value": true
        }
      ],
      "timeoutInMillisecond": 10000
    },
    "confirmBeforeExecute": false,
    "datasource": {
      "id": "MySQL_TestDB",
      "isAutoGenerated": false,
      "name": "MySQL_TestDB",
      "pluginId": "mysql-plugin"
    },
    "dynamicBindingPathList": [],
    "executeOnLoad": false,
    "name": "Query1",
    "pageId": "SnowflakeDB_Page",
    "userSetOnLoad": false
  }
}