{
  "gitSyncId": "649135437cb8515629f9868a_649135487cb8515629f987b7",
  "id": "UQI_Query9",
  "pluginId": "postgres-plugin",
  "pluginType": "DB",
  "unpublishedAction": {
    "actionConfiguration": {
      "body": "SELECT * FROM users ORDER BY id LIMIT 10;",
      "encodeParamsToggle": true,
      "paginationType": "NONE",
      "pluginSpecifiedTemplates": [
        {
          "value": true
        }
      ],
      "timeoutInMillisecond": 10000
    },
    "confirmBeforeExecute": false,
    "datasource": {
      "id": "PostGreSQL_2",
      "isAutoGenerated": false,
      "name": "PostGreSQL_2",
      "pluginId": "postgres-plugin"
    },
    "dynamicBindingPathList": [],
    "executeOnLoad": false,
    "name": "Query9",
    "pageId": "UQI",
    "userSetOnLoad": false
  }
}