{
  "borderRadius": "{{appsmith.theme.borderRadius.appBorderRadius}}",
  "bottomRow": 62,
  "boxShadow": "none",
  "displayName": "Camera",
  "dynamicBindingPathList": [
    {
      "key": "borderRadius"
    }
  ],
  "hideCard": false,
  "iconSVG": "/static/media/icon.79c0d6de26a15bf464f2485130faa461.svg",
  "isCanvas": false,
  "isDeprecated": false,
  "isDisabled": false,
  "isLoading": false,
  "isMirrored": true,
  "isVisible": true,
  "key": "6wo7q9imeb",
  "leftColumn": 1,
  "mode": "CAMERA",
  "parentColumnSpace": 17.9375,
  "parentId": "0",
  "parentRowSpace": 10,
  "renderMode": "CANVAS",
  "rightColumn": 26,
  "searchTags": [
    "photo",
    "video recorder"
  ],
  "topRow": 29,
  "type": "CAMERA_WIDGET",
  "version": 1,
  "widgetId": "jbxfg2rjwa",
  "widgetName": "Camera1"
}